{
  "project_info": {
    "project_number": "281918023623",
    "project_id": "esmanager-3afd1",
    "storage_bucket": "esmanager-3afd1.appspot.com"
  },
  "client": [
    {
      "client_info": {
        "mobilesdk_app_id": "1:281918023623:android:5d8558f9497ab76df0dbe2",
        "android_client_info": {
          "package_name": "com.thatmg393.esmanager"
        }
      },
      "oauth_client": [
        {
          "client_id": "281918023623-4fnr41rq5n79adnb1og496grlbt52prn.apps.googleusercontent.com",
          "client_type": 3
        }
      ],
      "api_key": [
        {
          "current_key": "AIzaSyAlPFjwdZaV3zFtzRQNqDDgltolcXS833Q"
        }
      ],
      "services": {
        "appinvite_service": {
          "other_platform_oauth_client": [
            {
              "client_id": "281918023623-4fnr41rq5n79adnb1og496grlbt52prn.apps.googleusercontent.com",
              "client_type": 3
            }
          ]
        }
      }
    }
  ],
  "configuration_version": "1"
}